setup.py
huigege_page_views/__init__.py
huigege_page_views/page_views.py
huigege_page_views.egg-info/PKG-INFO
huigege_page_views.egg-info/SOURCES.txt
huigege_page_views.egg-info/dependency_links.txt
huigege_page_views.egg-info/top_level.txt
huigege_page_views.egg-info/zip-safe