Metadata-Version: 1.0
Name: huigege-page-views
Version: 0.0.2
Summary: views_page
Home-page: https://github.com/wan5198
Author: Huigege
Author-email: wan5198@qq.com
License: UNKNOWN
Platform: UNKNOWN
